{
  "info": {
    "adult": false,
    "backdrop_path": "/rMvPXy8PUjj1o8o1pzgQbdNCsvj.jpg",
    "belongs_to_collection": {
      "id": 126125,
      "name": "The Expendables Collection",
      "poster_path": "/zwnCtNpHa6TFI1z20LPFgdY2Qks.jpg",
      "backdrop_path": "/lA7oDSt6LkyDqtbFGbyuG0afmTI.jpg"
    },
    "budget": 100000000,
    "genres": [
      {
        "id": 28,
        "name": "Action"
      },
      {
        "id": 12,
        "name": "Adventure"
      },
      {
        "id": 53,
        "name": "Thriller"
      }
    ],
    "homepage": "https://expendables.movie/",
    "id": 299054,
    "imdb_id": "tt3291150",
    "original_language": "en",
    "original_title": "Expend4bles",
    "overview": "Armed with every weapon they can get their hands on and the skills to use them, The Expendables are the world\u2019s last line of defense and the team that gets called when all other options are off the table. But new team members with new styles and tactics are going to give \u201cnew blood\u201d a whole new meaning.",
    "popularity": 839.656,
    "poster_path": "/nbrqj9q8WubD3QkYm7n3GhjN7kE.jpg",
    "production_companies": [
      {
        "id": 1020,
        "logo_path": "/kuUIHNwMec4dwOLghDhhZJzHZTd.png",
        "name": "Millennium Media",
        "origin_country": "US"
      },
      {
        "id": 48738,
        "logo_path": null,
        "name": "Campbell Grobman Films",
        "origin_country": "US"
      },
      {
        "id": 1632,
        "logo_path": "/cisLn1YAUuptXVBa0xjq7ST9cH0.png",
        "name": "Lionsgate",
        "origin_country": "US"
      }
    ],
    "production_countries": [
      {
        "iso_3166_1": "US",
        "name": "United States of America"
      }
    ],
    "release_date": "2023-09-15",
    "revenue": 46869371,
    "runtime": 103,
    "spoken_languages": [
      {
        "english_name": "English",
        "iso_639_1": "en",
        "name": "English"
      }
    ],
    "status": "Released",
    "tagline": "They'll die when they're dead.",
    "title": "Expend4bles",
    "video": false,
    "vote_average": 6.208,
    "vote_count": 192
  },
  "images": [
    {
      "aspect_ratio": 0.667,
      "height": 3000,
      "iso_639_1": "uk",
      "file_path": "/xwGpfpc1nU2Fmwaos4XArg8mBR8.jpg",
      "vote_average": 5.456,
      "vote_count": 5,
      "width": 2000
    },
    {
      "aspect_ratio": 0.667,
      "height": 3000,
      "iso_639_1": "en",
      "file_path": "/nbrqj9q8WubD3QkYm7n3GhjN7kE.jpg",
      "vote_average": 5.39,
      "vote_count": 6,
      "width": 2000
    },
    {
      "aspect_ratio": 0.667,
      "height": 3000,
      "iso_639_1": "en",
      "file_path": "/iwsMu0ehRPbtaSxqiaUDQB9qMWT.jpg",
      "vote_average": 5.39,
      "vote_count": 6,
      "width": 2000
    },
    {
      "aspect_ratio": 0.667,
      "height": 2568,
      "iso_639_1": "zh",
      "file_path": "/ySYumRgZn0Y6r1vulDCbEV9Ma2B.jpg",
      "vote_average": 5.388,
      "vote_count": 4,
      "width": 1712
    },
    {
      "aspect_ratio": 0.667,
      "height": 3000,
      "iso_639_1": null,
      "file_path": "/3qaV2KgMAehI233ke10eFty0zce.jpg",
      "vote_average": 5.384,
      "vote_count": 2,
      "width": 2000
    },
    {
      "aspect_ratio": 0.667,
      "height": 3000,
      "iso_639_1": "pt",
      "file_path": "/dQxlUkhKGILgq9jbVEe3WPaiW2q.jpg",
      "vote_average": 5.384,
      "vote_count": 2,
      "width": 2000
    },
    {
      "aspect_ratio": 0.667,
      "height": 2880,
      "iso_639_1": "uk",
      "file_path": "/tWWGWUpf6po2CilcVYQw0WWOuZN.jpg",
      "vote_average": 5.338,
      "vote_count": 13,
      "width": 1920
    },
    {
      "aspect_ratio": 0.72,
      "height": 1500,
      "iso_639_1": "dz",
      "file_path": "/q8PeV8Vi9kaiBuH9ZAEIPKSjK3b.jpg",
      "vote_average": 5.318,
      "vote_count": 3,
      "width": 1080
    },
    {
      "aspect_ratio": 0.667,
      "height": 2339,
      "iso_639_1": "es",
      "file_path": "/g6bfq26jmzEGNGMw768Fwu6OmdZ.jpg",
      "vote_average": 5.318,
      "vote_count": 3,
      "width": 1560
    },
    {
      "aspect_ratio": 0.667,
      "height": 3000,
      "iso_639_1": "zh",
      "file_path": "/2anbBID1Ew5McZMLChYSHcawUHH.jpg",
      "vote_average": 5.318,
      "vote_count": 3,
      "width": 2000
    },
    {
      "aspect_ratio": 0.667,
      "height": 1500,
      "iso_639_1": "ru",
      "file_path": "/nBCvzyY9POTMBb0Fi85E7Szikgc.jpg",
      "vote_average": 5.312,
      "vote_count": 1,
      "width": 1000
    },
    {
      "aspect_ratio": 0.667,
      "height": 3000,
      "iso_639_1": "zh",
      "file_path": "/mng6i4wn16k8OK1Tl8XBI6TjzGf.jpg",
      "vote_average": 5.312,
      "vote_count": 1,
      "width": 2000
    },
    {
      "aspect_ratio": 0.7,
      "height": 1418,
      "iso_639_1": "no",
      "file_path": "/Ek2tVfHVhV2fpAl7uDuZCRXfh4.jpg",
      "vote_average": 5.312,
      "vote_count": 1,
      "width": 992
    },
    {
      "aspect_ratio": 0.667,
      "height": 2850,
      "iso_639_1": "ko",
      "file_path": "/y8L3N9KGGal2CiNgIJ5tP5W9iAF.jpg",
      "vote_average": 5.312,
      "vote_count": 1,
      "width": 1900
    },
    {
      "aspect_ratio": 0.667,
      "height": 2250,
      "iso_639_1": "sk",
      "file_path": "/8jYewxTnP2z8cZofTiBcyml86OF.jpg",
      "vote_average": 5.312,
      "vote_count": 1,
      "width": 1500
    },
    {
      "aspect_ratio": 0.667,
      "height": 1500,
      "iso_639_1": "he",
      "file_path": "/hZUAKl8VvGQb7sO78Nz1F8QB0Ep.jpg",
      "vote_average": 5.312,
      "vote_count": 1,
      "width": 1000
    },
    {
      "aspect_ratio": 0.667,
      "height": 3000,
      "iso_639_1": "es",
      "file_path": "/oCP9phxiYD96Lt5PM1WbDX93zns.jpg",
      "vote_average": 5.312,
      "vote_count": 1,
      "width": 2000
    },
    {
      "aspect_ratio": 0.667,
      "height": 1500,
      "iso_639_1": "en",
      "file_path": "/dmXrjuF91REomXa5IY9n599MTu9.jpg",
      "vote_average": 5.312,
      "vote_count": 1,
      "width": 1000
    },
    {
      "aspect_ratio": 0.667,
      "height": 3000,
      "iso_639_1": "ro",
      "file_path": "/bk9cOOB0wQbhTBcrE7QhjtsIbJV.jpg",
      "vote_average": 5.312,
      "vote_count": 1,
      "width": 2000
    },
    {
      "aspect_ratio": 0.667,
      "height": 3000,
      "iso_639_1": "ro",
      "file_path": "/d359Wj3S8GTsQIz0EKSKA2STqhs.jpg",
      "vote_average": 5.312,
      "vote_count": 1,
      "width": 2000
    },
    {
      "aspect_ratio": 0.667,
      "height": 3000,
      "iso_639_1": "de",
      "file_path": "/p1TCV7St44sjwunaGSQ73vdFFkS.jpg",
      "vote_average": 5.312,
      "vote_count": 1,
      "width": 2000
    },
    {
      "aspect_ratio": 0.667,
      "height": 3000,
      "iso_639_1": "en",
      "file_path": "/nLOw900kDcbvsSs5YshUXRvWS0Z.jpg",
      "vote_average": 5.276,
      "vote_count": 12,
      "width": 2000
    },
    {
      "aspect_ratio": 0.667,
      "height": 2880,
      "iso_639_1": "uk",
      "file_path": "/jo7rJR8CyBh1gpoSdQqBoXQF69t.jpg",
      "vote_average": 5.27,
      "vote_count": 10,
      "width": 1920
    },
    {
      "aspect_ratio": 0.675,
      "height": 1778,
      "iso_639_1": "pt",
      "file_path": "/eLFNvdIkDBvADDIa6D5CAlPJPh8.jpg",
      "vote_average": 5.246,
      "vote_count": 2,
      "width": 1200
    },
    {
      "aspect_ratio": 0.667,
      "height": 2099,
      "iso_639_1": "ru",
      "file_path": "/iaWzZx5G9Ydh0DIyluTvtNS6Aw3.jpg",
      "vote_average": 5.246,
      "vote_count": 2,
      "width": 1400
    },
    {
      "aspect_ratio": 0.735,
      "height": 1360,
      "iso_639_1": "fr",
      "file_path": "/nXh6kIdJQsjBHBTTTFOW8MlScm7.jpg",
      "vote_average": 5.246,
      "vote_count": 2,
      "width": 1000
    },
    {
      "aspect_ratio": 0.667,
      "height": 1500,
      "iso_639_1": "de",
      "file_path": "/pRvzp12qRI36uzIQtvAN6V5Yap.jpg",
      "vote_average": 5.246,
      "vote_count": 2,
      "width": 1000
    },
    {
      "aspect_ratio": 0.703,
      "height": 1080,
      "iso_639_1": "es",
      "file_path": "/rX2UFZXpdhg3FJt99THCZuP94ew.jpg",
      "vote_average": 5.246,
      "vote_count": 2,
      "width": 759
    },
    {
      "aspect_ratio": 0.667,
      "height": 1500,
      "iso_639_1": "en",
      "file_path": "/56Tsa1yOFdpXmbUJKf4mkOsy5bE.jpg",
      "vote_average": 5.246,
      "vote_count": 2,
      "width": 1000
    },
    {
      "aspect_ratio": 0.667,
      "height": 3000,
      "iso_639_1": "de",
      "file_path": "/hbYBKNuUyMnDObDUSH7u5qSiUET.jpg",
      "vote_average": 5.246,
      "vote_count": 2,
      "width": 2000
    },
    {
      "aspect_ratio": 0.667,
      "height": 3000,
      "iso_639_1": "uk",
      "file_path": "/ltup9iFYhm9gTJlempY2w81KXqD.jpg",
      "vote_average": 5.19,
      "vote_count": 5,
      "width": 2000
    },
    {
      "aspect_ratio": 0.675,
      "height": 2963,
      "iso_639_1": "en",
      "file_path": "/wNKxhqU1omnU5ZZ85SdBM4IQvji.jpg",
      "vote_average": 5.18,
      "vote_count": 3,
      "width": 2000
    },
    {
      "aspect_ratio": 0.673,
      "height": 1605,
      "iso_639_1": "en",
      "file_path": "/o1YHEsGCMFMy0nkrnKM2bPA208a.jpg",
      "vote_average": 5.18,
      "vote_count": 3,
      "width": 1080
    },
    {
      "aspect_ratio": 0.7,
      "height": 1418,
      "iso_639_1": "no",
      "file_path": "/yfuMIO78xaEK9CJS9mX6AuRMAFl.jpg",
      "vote_average": 5.172,
      "vote_count": 1,
      "width": 992
    },
    {
      "aspect_ratio": 0.667,
      "height": 1721,
      "iso_639_1": "he",
      "file_path": "/jNByf4xBvzaheJAsjjN59XzQQn3.jpg",
      "vote_average": 5.172,
      "vote_count": 1,
      "width": 1148
    },
    {
      "aspect_ratio": 0.711,
      "height": 1368,
      "iso_639_1": "cn",
      "file_path": "/1EoEdLw6VABkEh3wk5LLKLuxj0c.jpg",
      "vote_average": 5.172,
      "vote_count": 1,
      "width": 972
    },
    {
      "aspect_ratio": 0.667,
      "height": 3000,
      "iso_639_1": "he",
      "file_path": "/oPskJ18GeLqioSUCM3mwLp98ZA0.jpg",
      "vote_average": 5.172,
      "vote_count": 1,
      "width": 2000
    },
    {
      "aspect_ratio": 0.667,
      "height": 3000,
      "iso_639_1": "de",
      "file_path": "/heAT73WLhggbFeTFhmDDH5CM6cO.jpg",
      "vote_average": 5.172,
      "vote_count": 1,
      "width": 2000
    },
    {
      "aspect_ratio": 0.667,
      "height": 2852,
      "iso_639_1": "ko",
      "file_path": "/dWR8OTRCcYDbBmd8GKsyJT73kU2.jpg",
      "vote_average": 5.172,
      "vote_count": 1,
      "width": 1901
    },
    {
      "aspect_ratio": 0.7,
      "height": 2286,
      "iso_639_1": "es",
      "file_path": "/61vG9UNWfH5en1WoLxGtROXU9o7.jpg",
      "vote_average": 5.172,
      "vote_count": 1,
      "width": 1600
    },
    {
      "aspect_ratio": 0.667,
      "height": 1080,
      "iso_639_1": "no",
      "file_path": "/vhgrINxKwRZWmeYC7wI7x8nixok.jpg",
      "vote_average": 5.106,
      "vote_count": 2,
      "width": 720
    },
    {
      "aspect_ratio": 0.667,
      "height": 3000,
      "iso_639_1": "uk",
      "file_path": "/9f7GNpsVlwiCLPCixgVC3FY9nMp.jpg",
      "vote_average": 5.1,
      "vote_count": 13,
      "width": 2000
    },
    {
      "aspect_ratio": 0.667,
      "height": 1200,
      "iso_639_1": "it",
      "file_path": "/lRYc5e6EPar9eRGceqj7LITb4Er.jpg",
      "vote_average": 0.0,
      "vote_count": 0,
      "width": 800
    },
    {
      "aspect_ratio": 0.72,
      "height": 1500,
      "iso_639_1": "fr",
      "file_path": "/sFPJVBr7JjdVwJ9bdxOdX6ERu3t.jpg",
      "vote_average": 0.0,
      "vote_count": 0,
      "width": 1080
    },
    {
      "aspect_ratio": 0.675,
      "height": 1926,
      "iso_639_1": "el",
      "file_path": "/c3OQhj39tzTtq0VF7mwTR2t45pD.jpg",
      "vote_average": 0.0,
      "vote_count": 0,
      "width": 1300
    },
    {
      "aspect_ratio": 0.71,
      "height": 1080,
      "iso_639_1": "cn",
      "file_path": "/gTGV1TS1qCRVNqqLQwkAtpo6Z6i.jpg",
      "vote_average": 0.0,
      "vote_count": 0,
      "width": 767
    },
    {
      "aspect_ratio": 0.675,
      "height": 779,
      "iso_639_1": "lo",
      "file_path": "/mRz8jP0UbwyAGnEFl9Q0UDNK5J1.jpg",
      "vote_average": 0.0,
      "vote_count": 0,
      "width": 526
    },
    {
      "aspect_ratio": 0.667,
      "height": 1500,
      "iso_639_1": "vi",
      "file_path": "/lMFi3ri8h6BYtjqNwMe9y69kTwQ.jpg",
      "vote_average": 0.0,
      "vote_count": 0,
      "width": 1000
    },
    {
      "aspect_ratio": 0.697,
      "height": 2807,
      "iso_639_1": "el",
      "file_path": "/5UCPLA1M4sNuepWAgWd50DIzBDD.jpg",
      "vote_average": 0.0,
      "vote_count": 0,
      "width": 1957
    },
    {
      "aspect_ratio": 0.667,
      "height": 3000,
      "iso_639_1": "th",
      "file_path": "/96RsfwvEljl0tuXpHuUy6xLqr3U.jpg",
      "vote_average": 0.0,
      "vote_count": 0,
      "width": 2000
    },
    {
      "aspect_ratio": 0.675,
      "height": 1440,
      "iso_639_1": "lo",
      "file_path": "/ow3txFF4guPdwlGWiustpTgqNkA.jpg",
      "vote_average": 0.0,
      "vote_count": 0,
      "width": 972
    },
    {
      "aspect_ratio": 0.706,
      "height": 1814,
      "iso_639_1": "ja",
      "file_path": "/x6OqdmVpCXWrV37g0989DuCgSoQ.jpg",
      "vote_average": 0.0,
      "vote_count": 0,
      "width": 1280
    },
    {
      "aspect_ratio": 0.667,
      "height": 3000,
      "iso_639_1": null,
      "file_path": "/DnkPKMjypFqZrzlStud5Z4WJ51.jpg",
      "vote_average": 0.0,
      "vote_count": 0,
      "width": 2000
    },
    {
      "aspect_ratio": 0.667,
      "height": 3000,
      "iso_639_1": "zh",
      "file_path": "/oMapKrdPq6sODoOiVhtlQo9XsDS.jpg",
      "vote_average": 0.0,
      "vote_count": 0,
      "width": 2000
    },
    {
      "aspect_ratio": 0.667,
      "height": 3000,
      "iso_639_1": "zh",
      "file_path": "/tD5ShJ2PP8YB95oaRJJVbwOZN3R.jpg",
      "vote_average": 0.0,
      "vote_count": 0,
      "width": 2000
    },
    {
      "aspect_ratio": 0.667,
      "height": 1500,
      "iso_639_1": "vi",
      "file_path": "/2Sqea3Kwbf63TpOyrQzLMba1Owv.jpg",
      "vote_average": 0.0,
      "vote_count": 0,
      "width": 1000
    },
    {
      "aspect_ratio": 0.667,
      "height": 1500,
      "iso_639_1": "vi",
      "file_path": "/j8VqMvgaP3pQvUy2OHxCpZGNuIX.jpg",
      "vote_average": 0.0,
      "vote_count": 0,
      "width": 1000
    },
    {
      "aspect_ratio": 0.667,
      "height": 1500,
      "iso_639_1": "vi",
      "file_path": "/5djipaMQfD3BfWbuo2PQsIspWUd.jpg",
      "vote_average": 0.0,
      "vote_count": 0,
      "width": 1000
    },
    {
      "aspect_ratio": 0.667,
      "height": 1500,
      "iso_639_1": "vi",
      "file_path": "/udAnjYfYrFxaYHVb29QiGvzY35k.jpg",
      "vote_average": 0.0,
      "vote_count": 0,
      "width": 1000
    },
    {
      "aspect_ratio": 0.667,
      "height": 1500,
      "iso_639_1": "vi",
      "file_path": "/iU8jmeyjRuKCLeGdKAUREYrSegp.jpg",
      "vote_average": 0.0,
      "vote_count": 0,
      "width": 1000
    },
    {
      "aspect_ratio": 0.667,
      "height": 1500,
      "iso_639_1": "vi",
      "file_path": "/uE1XQVcWUOp3N5Vj1G5rhwI7c2Q.jpg",
      "vote_average": 0.0,
      "vote_count": 0,
      "width": 1000
    },
    {
      "aspect_ratio": 0.667,
      "height": 1500,
      "iso_639_1": "vi",
      "file_path": "/dlVBvm6HX328NfkDgBdLBjMssYJ.jpg",
      "vote_average": 0.0,
      "vote_count": 0,
      "width": 1000
    },
    {
      "aspect_ratio": 0.667,
      "height": 1500,
      "iso_639_1": "vi",
      "file_path": "/6SnL1aZf9s1nZ9zJArG6xwAl05h.jpg",
      "vote_average": 0.0,
      "vote_count": 0,
      "width": 1000
    },
    {
      "aspect_ratio": 0.667,
      "height": 1500,
      "iso_639_1": "vi",
      "file_path": "/bfwdODnccqTwAmwjjt36DShEpdN.jpg",
      "vote_average": 0.0,
      "vote_count": 0,
      "width": 1000
    },
    {
      "aspect_ratio": 0.667,
      "height": 1500,
      "iso_639_1": "vi",
      "file_path": "/4IbHyZOyDtFOav5f2C4ZF4Y1nbv.jpg",
      "vote_average": 0.0,
      "vote_count": 0,
      "width": 1000
    },
    {
      "aspect_ratio": 0.667,
      "height": 1500,
      "iso_639_1": "vi",
      "file_path": "/1NvFMPNJHlMuz1oIupxmOUdNtgy.jpg",
      "vote_average": 0.0,
      "vote_count": 0,
      "width": 1000
    },
    {
      "aspect_ratio": 0.667,
      "height": 1920,
      "iso_639_1": "zh",
      "file_path": "/eWUst3pirGbJrdabyWBKCUsQPjo.jpg",
      "vote_average": 0.0,
      "vote_count": 0,
      "width": 1280
    },
    {
      "aspect_ratio": 0.672,
      "height": 1290,
      "iso_639_1": "en",
      "file_path": "/6TRB6fvR8TbDYtIBnXHOLt1wMI8.jpg",
      "vote_average": 0.0,
      "vote_count": 0,
      "width": 867
    },
    {
      "aspect_ratio": 0.667,
      "height": 2700,
      "iso_639_1": "pt",
      "file_path": "/f7i9urXYuWdmKWPWHUeQj4AGYez.jpg",
      "vote_average": 0.0,
      "vote_count": 0,
      "width": 1800
    },
    {
      "aspect_ratio": 0.667,
      "height": 3000,
      "iso_639_1": "pt",
      "file_path": "/7D56cpIldaRRZzOnvXoe1spDiqD.jpg",
      "vote_average": 0.0,
      "vote_count": 0,
      "width": 2000
    },
    {
      "aspect_ratio": 0.667,
      "height": 750,
      "iso_639_1": "en",
      "file_path": "/1tyGgFHOy8P01yykk5dB8k59QuA.jpg",
      "vote_average": 0.0,
      "vote_count": 0,
      "width": 500
    },
    {
      "aspect_ratio": 0.667,
      "height": 1500,
      "iso_639_1": "hr",
      "file_path": "/y0J6XXsYzAtd6Bn2YSt5Uloontl.jpg",
      "vote_average": 0.0,
      "vote_count": 0,
      "width": 1000
    },
    {
      "aspect_ratio": 0.667,
      "height": 3000,
      "iso_639_1": null,
      "file_path": "/62ZGTAdCcmdfVwF7bvAyfvRXrQz.jpg",
      "vote_average": 0.0,
      "vote_count": 0,
      "width": 2000
    },
    {
      "aspect_ratio": 0.667,
      "height": 3000,
      "iso_639_1": "zh",
      "file_path": "/wLlrePkNBXdNH81ehGdCUuYgxoy.jpg",
      "vote_average": 0.0,
      "vote_count": 0,
      "width": 2000
    },
    {
      "aspect_ratio": 0.667,
      "height": 2475,
      "iso_639_1": "en",
      "file_path": "/iOSMqVfv8H127jz6WadRyZncYqj.jpg",
      "vote_average": 0.0,
      "vote_count": 0,
      "width": 1650
    },
    {
      "aspect_ratio": 0.667,
      "height": 2835,
      "iso_639_1": "sv",
      "file_path": "/ybKCCC78VAeJQIzPc1ENQ0pzJ2w.jpg",
      "vote_average": 0.0,
      "vote_count": 0,
      "width": 1890
    },
    {
      "aspect_ratio": 0.667,
      "height": 1000,
      "iso_639_1": "fr",
      "file_path": "/gurcaBR85BDK3puQlmjLqKfNfWl.jpg",
      "vote_average": 0.0,
      "vote_count": 0,
      "width": 667
    },
    {
      "aspect_ratio": 0.675,
      "height": 1778,
      "iso_639_1": "pt",
      "file_path": "/v6cq8CMGrQGTCtWtm2LK77CM2Ux.jpg",
      "vote_average": 0.0,
      "vote_count": 0,
      "width": 1200
    },
    {
      "aspect_ratio": 0.667,
      "height": 750,
      "iso_639_1": "pl",
      "file_path": "/o4oEqbmZcBwhsVJ1qhlwOF4asVO.jpg",
      "vote_average": 0.0,
      "vote_count": 0,
      "width": 500
    },
    {
      "aspect_ratio": 0.667,
      "height": 3000,
      "iso_639_1": "de",
      "file_path": "/ibCeIrm25oWdUdr9MGlNCdXJ0z2.jpg",
      "vote_average": 0.0,
      "vote_count": 0,
      "width": 2000
    },
    {
      "aspect_ratio": 0.667,
      "height": 3000,
      "iso_639_1": "de",
      "file_path": "/tnahWRY6HSQalwd6CKD4CHAWEoz.jpg",
      "vote_average": 0.0,
      "vote_count": 0,
      "width": 2000
    },
    {
      "aspect_ratio": 0.667,
      "height": 3000,
      "iso_639_1": "fa",
      "file_path": "/8aiAtELPBnNNAo5Z8GzyZYmo77Q.jpg",
      "vote_average": 0.0,
      "vote_count": 0,
      "width": 2000
    },
    {
      "aspect_ratio": 0.667,
      "height": 1500,
      "iso_639_1": "it",
      "file_path": "/75p8utAXp2mEfSZKW1HYHGfRbv3.jpg",
      "vote_average": 0.0,
      "vote_count": 0,
      "width": 1000
    },
    {
      "aspect_ratio": 0.703,
      "height": 1536,
      "iso_639_1": "ru",
      "file_path": "/6bitMRd0XPG7xLAQ1WY4xGz7n1X.jpg",
      "vote_average": 0.0,
      "vote_count": 0,
      "width": 1080
    },
    {
      "aspect_ratio": 0.703,
      "height": 1536,
      "iso_639_1": "ru",
      "file_path": "/fW6GmibYQgaVwqLcZvZRLLwIosi.jpg",
      "vote_average": 0.0,
      "vote_count": 0,
      "width": 1080
    },
    {
      "aspect_ratio": 0.703,
      "height": 1536,
      "iso_639_1": "ru",
      "file_path": "/cs2PLdghzi6jW2hvMNsRm9PJSpP.jpg",
      "vote_average": 0.0,
      "vote_count": 0,
      "width": 1080
    },
    {
      "aspect_ratio": 0.703,
      "height": 1536,
      "iso_639_1": "ru",
      "file_path": "/6AEGcXW7LpGg1I5rQYDfRPxugO7.jpg",
      "vote_average": 0.0,
      "vote_count": 0,
      "width": 1080
    },
    {
      "aspect_ratio": 0.703,
      "height": 1536,
      "iso_639_1": "ru",
      "file_path": "/qzNWXNnbxFMJXsswdEGQFCCjMSK.jpg",
      "vote_average": 0.0,
      "vote_count": 0,
      "width": 1080
    },
    {
      "aspect_ratio": 0.703,
      "height": 1536,
      "iso_639_1": "ru",
      "file_path": "/aejdmfDSnIOS0do9Uj3247jXUu1.jpg",
      "vote_average": 0.0,
      "vote_count": 0,
      "width": 1080
    },
    {
      "aspect_ratio": 0.703,
      "height": 1536,
      "iso_639_1": "ru",
      "file_path": "/ln0cRBzZK6VCGLIWWJSTZ2VRBG3.jpg",
      "vote_average": 0.0,
      "vote_count": 0,
      "width": 1080
    },
    {
      "aspect_ratio": 0.703,
      "height": 1536,
      "iso_639_1": "ru",
      "file_path": "/fBPUGbMYMEwZPqKffShYDSNFCVe.jpg",
      "vote_average": 0.0,
      "vote_count": 0,
      "width": 1080
    },
    {
      "aspect_ratio": 0.703,
      "height": 1536,
      "iso_639_1": "ru",
      "file_path": "/lft31wwrRswh2WA6o7x0s8zer0j.jpg",
      "vote_average": 0.0,
      "vote_count": 0,
      "width": 1080
    },
    {
      "aspect_ratio": 0.667,
      "height": 1192,
      "iso_639_1": "cs",
      "file_path": "/pbtV4E8qsOrRASJ5KLIMshkNYJa.jpg",
      "vote_average": 0.0,
      "vote_count": 0,
      "width": 795
    },
    {
      "aspect_ratio": 0.667,
      "height": 2475,
      "iso_639_1": "en",
      "file_path": "/8XFj6ZVZM3toQI2JTAOgLiJQrMn.jpg",
      "vote_average": 0.0,
      "vote_count": 0,
      "width": 1650
    },
    {
      "aspect_ratio": 0.667,
      "height": 3000,
      "iso_639_1": "fr",
      "file_path": "/78C8PQ6bcmMkIwaLEyZ2TSriLI.jpg",
      "vote_average": 0.0,
      "vote_count": 0,
      "width": 2000
    },
    {
      "aspect_ratio": 0.667,
      "height": 3000,
      "iso_639_1": "fr",
      "file_path": "/mflUzRIqagx32LgqhsFobv7T70o.jpg",
      "vote_average": 0.0,
      "vote_count": 0,
      "width": 2000
    },
    {
      "aspect_ratio": 0.667,
      "height": 1500,
      "iso_639_1": "en",
      "file_path": "/h6YrwRt0Qt88ovuSQYR3bKB7SO4.jpg",
      "vote_average": 0.0,
      "vote_count": 0,
      "width": 1000
    },
    {
      "aspect_ratio": 0.667,
      "height": 1500,
      "iso_639_1": "en",
      "file_path": "/ptvZbpXlEh1AX5ePre2IXhsSJbn.jpg",
      "vote_average": 0.0,
      "vote_count": 0,
      "width": 1000
    },
    {
      "aspect_ratio": 0.667,
      "height": 1500,
      "iso_639_1": "en",
      "file_path": "/64m54HUzVp3hmKdUi2N4YxdnQDY.jpg",
      "vote_average": 0.0,
      "vote_count": 0,
      "width": 1000
    },
    {
      "aspect_ratio": 0.667,
      "height": 1500,
      "iso_639_1": "en",
      "file_path": "/om2Fy63VYJKhQOkMqqRGmCc6iPd.jpg",
      "vote_average": 0.0,
      "vote_count": 0,
      "width": 1000
    },
    {
      "aspect_ratio": 0.667,
      "height": 1500,
      "iso_639_1": "en",
      "file_path": "/3svALw1aCJtW8alOcFgy8VVUXYW.jpg",
      "vote_average": 0.0,
      "vote_count": 0,
      "width": 1000
    },
    {
      "aspect_ratio": 0.667,
      "height": 3000,
      "iso_639_1": "en",
      "file_path": "/tvUaIIpdswGaOps3Ao3Z03BXJqi.jpg",
      "vote_average": 0.0,
      "vote_count": 0,
      "width": 2000
    },
    {
      "aspect_ratio": 0.667,
      "height": 1500,
      "iso_639_1": "en",
      "file_path": "/ko7YEaJMFzSX8TiydpX3jJUHEcc.jpg",
      "vote_average": 0.0,
      "vote_count": 0,
      "width": 1000
    },
    {
      "aspect_ratio": 0.672,
      "height": 1290,
      "iso_639_1": "en",
      "file_path": "/lmQFmBmX6W65qeL0XHXioMAMzp.jpg",
      "vote_average": 0.0,
      "vote_count": 0,
      "width": 867
    },
    {
      "aspect_ratio": 0.711,
      "height": 2736,
      "iso_639_1": "cn",
      "file_path": "/yIob4zrFNYpxZPpDEbafsdDCog5.jpg",
      "vote_average": 0.0,
      "vote_count": 0,
      "width": 1944
    },
    {
      "aspect_ratio": 0.667,
      "height": 3000,
      "iso_639_1": "es",
      "file_path": "/eXrlMoHyrxKAWog6l33fGAsnDeT.jpg",
      "vote_average": 0.0,
      "vote_count": 0,
      "width": 2000
    },
    {
      "aspect_ratio": 0.667,
      "height": 3000,
      "iso_639_1": "es",
      "file_path": "/3KoWOrkz0idvNbxo3DoMqQiXO5B.jpg",
      "vote_average": 0.0,
      "vote_count": 0,
      "width": 2000
    },
    {
      "aspect_ratio": 0.667,
      "height": 3000,
      "iso_639_1": "es",
      "file_path": "/xfDUy65MNgryq5jpRShmCrWKPy6.jpg",
      "vote_average": 0.0,
      "vote_count": 0,
      "width": 2000
    },
    {
      "aspect_ratio": 0.667,
      "height": 3000,
      "iso_639_1": "es",
      "file_path": "/1dn2qk0OFaHEAYRwQDvCvHd6QTY.jpg",
      "vote_average": 0.0,
      "vote_count": 0,
      "width": 2000
    }
  ],
  "reviews": [
    {
      "author": "CinemaSerf",
      "author_details": {
        "name": "CinemaSerf",
        "username": "Geronimo1967",
        "avatar_path": "/1kks3YnVkpyQxzw36CObFPvhL5f.jpg",
        "rating": 6.0
      },
      "content": "To be honest, there's very little new in this formulaic action adventure. It's the usual old who has got the launch codes mystery that sees Sly Stallone's \"Barney\" recruit his best mate \"Christmas\" (Jason Statham) and their lethal gang of expendables to thwart the ambitions of an unknown criminal mastermind who is hoping to arm a boat load of nuclear missiles and start WWIII. Thing is, tragedy strikes very early on in the film and \"Christmas\" is taken off the team that is sent to avenge that. Is he staying home to fester? Of course not, and lucky too - for soon he is trying to free his pals from captivity before all hell breaks loose. Plenty of pyrotechnics, a bit of contrived sexual chemistry (with Megan Fox's \"Gina\") and loads of bullets and missiles flying around keep the film moving along well enough, but the story is the thinnest of the thin; the baddie's identity is hardly a challenge to discover nor is the twist in the tale at the end remotely unexpected. Good to see that the acting colossus that is Dolph Lundgren is still getting on screen nowadays, but otherwise this really is unremarkable stuff that even the usually charismatic Statham can't really sustain.",
      "created_at": "2023-10-08T07:11:52.092Z",
      "id": "65225638ea84c7012d6ba258",
      "updated_at": "2023-10-08T07:11:52.202Z",
      "url": "https://www.themoviedb.org/review/65225638ea84c7012d6ba258"
    },
    {
      "author": "MovieGuys",
      "author_details": {
        "name": "",
        "username": "MovieGuys",
        "avatar_path": null,
        "rating": 4.0
      },
      "content": "A B grade action flick masquerading as a A list title. That's my reaction to Expendables 4.\r\n\r\nYes, its a tired formula but at least previous Expendable films in this cheesy action franchise, showed a little genuine enthusiasm and included a  cast of well worn but also well known, action stars. \r\n\r\nBy contrast, the latest flick is easily forgettable with a good number of cast members, I've never heard of or seen on screen, infrequently. \r\n\r\nIn summary, looks and behaves like a decidedly B grade action film with a sparse sprinkling of A grade action talent. Feels too, likes its going through the motions but not really delivering, if that makes sense.",
      "created_at": "2023-10-14T08:25:12.397Z",
      "id": "652a5068358da700e3bd1a32",
      "updated_at": "2023-10-16T03:18:07.571Z",
      "url": "https://www.themoviedb.org/review/652a5068358da700e3bd1a32"
    }
  ]
}
